extreme_parser/__init__.py
extreme_parser/amazon/__init__.py
extreme_parser/amazon/option/__init__.py
extreme_parser/amazon/option/model.py
extreme_parser/amazon/option/parse.py
extreme_parser/amazon/option/parse_test.py
extreme_parser/amazon/product/__init__.py
extreme_parser/amazon/product/model.py
extreme_parser/amazon/product/parse.py
extreme_parser/amazon/search/__init__.py
extreme_parser/amazon/search/model.py
extreme_parser/amazon/search/parse.py
extreme_parser/amazon/shop/__init__.py
extreme_parser/amazon/shop/model.py
extreme_parser/amazon/shop/parse.py
extreme_parser/etsy/__init__.py
extreme_parser/etsy/product/__init__.py
extreme_parser/etsy/product/model.py
extreme_parser/etsy/product/parse.py
extreme_parser/etsy/sold/__init__.py
extreme_parser/etsy/sold/parse.py
extreme_parser/etsy/sold/parse_test.py
extreme_parser/util/__init__.py
extreme_parser/util/parse.py
extreme_parser-3.8.1.dist-info/LICENSE
extreme_parser-3.8.1.dist-info/METADATA
extreme_parser-3.8.1.dist-info/WHEEL
extreme_parser-3.8.1.dist-info/top_level.txt
extreme_parser-3.8.1.dist-info/RECORD
